[
    {
        "doc_id": 0,
        "prompt_0": "Question: Cities control the amount of pollution that is allowed to come from cars. How does this most likely help people?\nAnswer: The air stays cleaner.",
        "prompt_1": "Question: Cities control the amount of pollution that is allowed to come from cars. How does this most likely help people?\nAnswer: Cars can travel at faster speeds.",
        "prompt_2": "Question: Cities control the amount of pollution that is allowed to come from cars. How does this most likely help people?\nAnswer: The skills of the drivers improve.",
        "prompt_3": "Question: Cities control the amount of pollution that is allowed to come from cars. How does this most likely help people?\nAnswer: It becomes safer to drive on the roads.",
        "logit_0": -12.828125,
        "truth": 0,
        "logit_1": -19.203125,
        "logit_2": -27.25,
        "logit_3": -22.0625,
        "acc": "1.0",
        "acc_norm": "0.0"
    },
    {
        "doc_id": 1,
        "prompt_0": "Question: Which statement correctly describes a physical characteristic of the Moon?\nAnswer: The Moon is made of hot gases.",
        "prompt_1": "Question: Which statement correctly describes a physical characteristic of the Moon?\nAnswer: The Moon is covered with many craters.",
        "prompt_2": "Question: Which statement correctly describes a physical characteristic of the Moon?\nAnswer: The Moon has many bodies of liquid water.",
        "prompt_3": "Question: Which statement correctly describes a physical characteristic of the Moon?\nAnswer: The Moon has the ability to give off its own light.",
        "logit_0": -18.59375,
        "truth": 1,
        "logit_1": -13.296875,
        "logit_2": -30.625,
        "logit_3": -22.125,
        "acc": "1.0",
        "acc_norm": "1.0"
    },
    {
        "doc_id": 2,
        "prompt_0": "Question: Which object in the solar system is orbited by a belt of asteroids?\nAnswer: Pluto",
        "prompt_1": "Question: Which object in the solar system is orbited by a belt of asteroids?\nAnswer: Saturn",
        "prompt_2": "Question: Which object in the solar system is orbited by a belt of asteroids?\nAnswer: the Sun",
        "prompt_3": "Question: Which object in the solar system is orbited by a belt of asteroids?\nAnswer: the Moon",
        "logit_0": -6.0390625,
        "truth": 2,
        "logit_1": -4.16015625,
        "logit_2": -7.06640625,
        "logit_3": -7.98046875,
        "acc": "0.0",
        "acc_norm": "0.0"
    },
    {
        "doc_id": 3,
        "prompt_0": "Question: Light waves that cross from an air medium to a water medium will\nAnswer: be focused into a straight line.",
        "prompt_1": "Question: Light waves that cross from an air medium to a water medium will\nAnswer: lose energy and dissipate.",
        "prompt_2": "Question: Light waves that cross from an air medium to a water medium will\nAnswer: change length and direction.",
        "prompt_3": "Question: Light waves that cross from an air medium to a water medium will\nAnswer: reflect off the water's surface.",
        "logit_0": -24.34375,
        "truth": 2,
        "logit_1": -18.109375,
        "logit_2": -15.28125,
        "logit_3": -13.03125,
        "acc": "0.0",
        "acc_norm": "0.0"
    },
    {
        "doc_id": 4,
        "prompt_0": "Question: How many valence electrons does selenium have?\nAnswer: 3",
        "prompt_1": "Question: How many valence electrons does selenium have?\nAnswer: 5",
        "prompt_2": "Question: How many valence electrons does selenium have?\nAnswer: 6",
        "prompt_3": "Question: How many valence electrons does selenium have?\nAnswer: 8",
        "logit_0": -5.23828125,
        "truth": 2,
        "logit_1": -5.43359375,
        "logit_2": -4.49609375,
        "logit_3": -5.31640625,
        "acc": "1.0",
        "acc_norm": "1.0"
    },
    {
        "doc_id": 5,
        "prompt_0": "Question: As a warm moist air mass moving northward collides with a strong cold air mass moving southward, what observations will most likely be made?\nAnswer: Thick fog develops.",
        "prompt_1": "Question: As a warm moist air mass moving northward collides with a strong cold air mass moving southward, what observations will most likely be made?\nAnswer: Temperatures increase.",
        "prompt_2": "Question: As a warm moist air mass moving northward collides with a strong cold air mass moving southward, what observations will most likely be made?\nAnswer: Clouds begin to form.",
        "prompt_3": "Question: As a warm moist air mass moving northward collides with a strong cold air mass moving southward, what observations will most likely be made?\nAnswer: Winds die down.",
        "logit_0": -17.328125,
        "truth": 2,
        "logit_1": -13.9921875,
        "logit_2": -13.1953125,
        "logit_3": -18.125,
        "acc": "1.0",
        "acc_norm": "1.0"
    }
]